{
  "generated_at": "2026-03-01T03:45:54+08:00",
  "source": "北单彩票数据",
  "period_no": "26031",
  "records": [
    {
      "game_id": 270,
      "period_no": "26031",
      "match_no": "330",
      "home_team": "桑德维肯",
      "away_team": "加尔斯",
      "league_name": "瑞典杯",
      "match_time": "2026-03-02T10:00:00Z",
      "end_time": "2026-03-03T01:55:00Z",
      "handicap": "1.5",
      "sale_status": "销售中",
      "collect_time": "2026-03-01T03:45:54.736759702+08:00",
      "odds": [
        {
          "option_key": "负",
          "odds_value": 1,
          "odds_type": "positive",
          "collect_time": "2026-02-27T14:17:44.577505Z"
        },
        {
          "option_key": "负",
          "odds_value": 1.12,
          "odds_type": "positive",
          "collect_time": "2026-02-27T18:44:44.477559Z"
        },
        {
          "option_key": "胜",
          "odds_value": 9.2,
          "odds_type": "positive",
          "collect_time": "2026-02-27T18:44:44.477559Z"
        },
        {
          "option_key": "负",
          "odds_value": 1.11,
          "odds_type": "positive",
          "collect_time": "2026-02-27T21:15:44.619127Z"
        },
        {
          "option_key": "胜",
          "odds_value": 9.73,
          "odds_type": "positive",
          "collect_time": "2026-02-27T21:15:44.619127Z"
        },
        {
          "option_key": "负",
          "odds_value": 1.19,
          "odds_type": "positive",
          "collect_time": "2026-02-28T00:23:44.555668Z"
        },
        {
          "option_key": "胜",
          "odds_value": 6.24,
          "odds_type": "positive",
          "collect_time": "2026-02-28T00:23:44.555668Z"
        },
        {
          "option_key": "胜",
          "odds_value": 13.01,
          "odds_type": "positive",
          "collect_time": "2026-02-28T09:11:44.551224Z"
        },
        {
          "option_key": "负",
          "odds_value": 1.08,
          "odds_type": "positive",
          "collect_time": "2026-02-28T09:11:44.551224Z"
        },
        {
          "option_key": "负",
          "odds_value": 1.11,
          "odds_type": "positive",
          "collect_time": "2026-02-28T11:14:44.554532Z"
        },
        {
          "option_key": "胜",
          "odds_value": 9.57,
          "odds_type": "positive",
          "collect_time": "2026-02-28T11:14:44.554532Z"
        },
        {
          "option_key": "胜",
          "odds_value": 8.2,
          "odds_type": "positive",
          "collect_time": "2026-02-28T11:17:44.531681Z"
        },
        {
          "option_key": "负",
          "odds_value": 1.13,
          "odds_type": "positive",
          "collect_time": "2026-02-28T11:17:44.531681Z"
        },
        {
          "option_key": "负",
          "odds_value": 1.08,
          "odds_type": "positive",
          "collect_time": "2026-02-28T13:26:44.472613Z"
        },
        {
          "option_key": "胜",
          "odds_value": 12.5,
          "odds_type": "positive",
          "collect_time": "2026-02-28T13:26:44.472613Z"
        },
        {
          "option_key": "胜",
          "odds_value": 12.54,
          "odds_type": "positive",
          "collect_time": "2026-02-28T13:57:44.507895Z"
        },
        {
          "option_key": "负",
          "odds_value": 1.08,
          "odds_type": "positive",
          "collect_time": "2026-02-28T13:57:44.507895Z"
        },
        {
          "option_key": "胜",
          "odds_value": 14.94,
          "odds_type": "positive",
          "collect_time": "2026-02-28T14:44:44.455227Z"
        },
        {
          "option_key": "负",
          "odds_value": 1.07,
          "odds_type": "positive",
          "collect_time": "2026-02-28T14:44:44.455227Z"
        },
        {
          "option_key": "胜",
          "odds_value": 17.34,
          "odds_type": "positive",
          "collect_time": "2026-02-28T14:56:44.487969Z"
        },
        {
          "option_key": "负",
          "odds_value": 1.06,
          "odds_type": "positive",
          "collect_time": "2026-02-28T14:56:44.487969Z"
        },
        {
          "option_key": "负",
          "odds_value": 1.06,
          "odds_type": "positive",
          "collect_time": "2026-02-28T15:50:44.515514Z"
        },
        {
          "option_key": "胜",
          "odds_value": 17.54,
          "odds_type": "positive",
          "collect_time": "2026-02-28T15:50:44.515514Z"
        },
        {
          "option_key": "负",
          "odds_value": 1.09,
          "odds_type": "positive",
          "collect_time": "2026-02-28T16:39:44.490881Z"
        },
        {
          "option_key": "胜",
          "odds_value": 11.33,
          "odds_type": "positive",
          "collect_time": "2026-02-28T16:39:44.490881Z"
        },
        {
          "option_key": "负",
          "odds_value": 1.09,
          "odds_type": "positive",
          "collect_time": "2026-02-28T16:56:44.54159Z"
        },
        {
          "option_key": "胜",
          "odds_value": 11.38,
          "odds_type": "positive",
          "collect_time": "2026-02-28T16:56:44.54159Z"
        },
        {
          "option_key": "负",
          "odds_value": 1.08,
          "odds_type": "positive",
          "collect_time": "2026-02-28T17:17:44.495468Z"
        },
        {
          "option_key": "胜",
          "odds_value": 12.48,
          "odds_type": "positive",
          "collect_time": "2026-02-28T17:17:44.495468Z"
        },
        {
          "option_key": "负",
          "odds_value": 1.08,
          "odds_type": "positive",
          "collect_time": "2026-02-28T17:27:44.508395Z"
        },
        {
          "option_key": "胜",
          "odds_value": 12.5,
          "odds_type": "positive",
          "collect_time": "2026-02-28T17:27:44.508395Z"
        },
        {
          "option_key": "胜",
          "odds_value": 12.63,
          "odds_type": "positive",
          "collect_time": "2026-02-28T17:50:44.466712Z"
        },
        {
          "option_key": "负",
          "odds_value": 1.08,
          "odds_type": "positive",
          "collect_time": "2026-02-28T17:50:44.466712Z"
        },
        {
          "option_key": "负",
          "odds_value": 1.09,
          "odds_type": "positive",
          "collect_time": "2026-02-28T18:41:44.574965Z"
        },
        {
          "option_key": "胜",
          "odds_value": 11.33,
          "odds_type": "positive",
          "collect_time": "2026-02-28T18:41:44.574965Z"
        },
        {
          "option_key": "负",
          "odds_value": 1.09,
          "odds_type": "positive",
          "collect_time": "2026-02-28T18:50:44.497219Z"
        },
        {
          "option_key": "胜",
          "odds_value": 11.38,
          "odds_type": "positive",
          "collect_time": "2026-02-28T18:50:44.497219Z"
        }
      ]
    }
  ],
  "total_count": 1
}